[
  {
    "user_name": "General Manager",
    "name": "Hoang Manh Hung",
    "password": "111",
    "center_name": null,
    "role_name": "TGD",
    "address": "Long Canh 86, vinhomes Thang Long, An Khanh, Hoai Duc, Ha Noi",
    "phone": "0828481258",
    "email": "generalmanager@magicpost.com",
    "deleted": false,
    "__v": 0
  },
  {
    "user_name": "DGD_TX_Hanoi_Manager",
    "name": "Nguyễn Văn Anh",
    "password": "111",
    "center_name": "DGD_TX_Hanoi",
    "role_name": "GDT",
    "address": "144 Sơn Tây st., Cau Giay dist, Thanh Hoa, Vietnam",
    "phone": "0974174952",
    "email": "txhanoi_manager@magicpost.transaction.com",
    "deleted": false,
    "__v": 0
  },
  {
    "user_name": "DGD_TX_Hanoi_Employee1",
    "name": "Phạm Văn Huyền",
    "password": "111",
    "center_name": "DGD_TX_Hanoi",
    "role_name": "GDV",
    "address": "281 Trần Duy Hưng st., Thanh Xuan dist, Ho Chi Minh, Vietnam",
    "phone": "0007120984",
    "email": "txhanoi_employee1@magicpost.transaction.com",
    "deleted": false,
    "__v": 0
  },
  {
    "user_name": "DGD_TX_Hanoi_Employee2",
    "name": "Nguyễn Văn Ngọc",
    "password": "111",
    "center_name": "DGD_TX_Hanoi",
    "role_name": "GDV",
    "address": "286 Sơn Tây st., Tay Ho dist, Da Nang, Vietnam",
    "phone": "0418740092",
    "email": "txhanoi_employee2@magicpost.transaction.com",
    "deleted": false,
    "__v": 0
  },
  {
    "user_name": "DGD_HD_Hanoi_Manager",
    "name": "Đinh Duy Huyền",
    "password": "111",
    "center_name": "DGD_HD_Hanoi",
    "role_name": "GDT",
    "address": "266 Trần Hưng Đạo st., Quoc Oai dist, Kon Tum, Vietnam",
    "phone": "0464976270",
    "email": "hdhanoi_manager@magicpost.transaction.com",
    "deleted": false,
    "__v": 0
  },
  {
    "user_name": "DGD_HD_Hanoi_Employee1",
    "name": "Phạm Văn Duy",
    "password": "111",
    "center_name": "DGD_HD_Hanoi",
    "role_name": "GDV",
    "address": "284 Nguyễn Thái Học st., Hoang Mai dist, Ho Chi Minh, Vietnam",
    "phone": "0126736571",
    "email": "hdhanoi_employee1@magicpost.transaction.com",
    "deleted": false,
    "__v": 0
  },
  {
    "user_name": "DGD_HD_Hanoi_Employee2",
    "name": "Trần Thu Ngọc",
    "password": "111",
    "center_name": "DGD_HD_Hanoi",
    "role_name": "GDV",
    "address": "0 Thái Hà st., Tay Ho dist, Kon Tum, Vietnam",
    "phone": "0005357197",
    "email": "hdhanoi_employee2@magicpost.transaction.com",
    "deleted": false,
    "__v": 0
  },
  {
    "user_name": "DGD_HK_Hanoi_Manager",
    "name": "Nguyễn Minh Duy",
    "password": "111",
    "center_name": "DGD_HK_Hanoi",
    "role_name": "GDT",
    "address": "271 Nguyễn Trung Trực st., Thanh Tri dist, Da Nang, Vietnam",
    "phone": "0891438813",
    "email": "hkhanoi_manager@magicpost.transaction.com",
    "deleted": false,
    "__v": 0
  },
  {
    "user_name": "DGD_HK_Hanoi_Employee1",
    "name": "Phạm Văn Duy",
    "password": "111",
    "center_name": "DGD_HK_Hanoi",
    "role_name": "GDV",
    "address": "234 Hoàng Hoa Thám st., Long Bien dist, Ho Chi Minh, Vietnam",
    "phone": "0497484801",
    "email": "hkhanoi_employee1@magicpost.transaction.com",
    "deleted": false,
    "__v": 0
  },
  {
    "user_name": "DGD_HK_Hanoi_Employee2",
    "name": "Đinh Văn Hùng",
    "password": "111",
    "center_name": "DGD_HK_Hanoi",
    "role_name": "GDV",
    "address": "38 Trúc Bạch st., Thach That dist, Thanh Hoa, Vietnam",
    "phone": "0666341859",
    "email": "hkhanoi_employee2@magicpost.transaction.com",
    "deleted": false,
    "__v": 0
  },
  {
    "user_name": "DGD_HB_HaiPhong_Manager",
    "name": "Hoàng Minh Huyền",
    "password": "111",
    "center_name": "DGD_HB_HaiPhong",
    "role_name": "GDT",
    "address": "19 Mai Anh Tuấn st., Cau Giay dist, Khanh Hoa, Vietnam",
    "phone": "0087567647",
    "email": "hbhaiphong_manager@magicpost.transaction.com",
    "deleted": false,
    "__v": 0
  },
  {
    "user_name": "DGD_HB_HaiPhong_Employee1",
    "name": "Trần Duy Duy",
    "password": "111",
    "center_name": "DGD_HB_HaiPhong",
    "role_name": "GDV",
    "address": "295 Vạn Bảo st., Cau Giay dist, Ha Noi, Vietnam",
    "phone": "0379363320",
    "email": "hbhaiphong_employee1@magicpost.transaction.com",
    "deleted": false,
    "__v": 0
  },
  {
    "user_name": "DGD_HB_HaiPhong_Employee2",
    "name": "Đinh Minh Huyền",
    "password": "111",
    "center_name": "DGD_HB_HaiPhong",
    "role_name": "GDV",
    "address": "140 Hoàng Hoa Thám st., Hoang Mai dist, Ha Noi, Vietnam",
    "phone": "0048976211",
    "email": "hbhaiphong_employee2@magicpost.transaction.com",
    "deleted": false,
    "__v": 0
  },
  {
    "user_name": "DGD_NQ_HaiPhong_Manager",
    "name": "Trần Minh Duy",
    "password": "111",
    "center_name": "DGD_NQ_HaiPhong",
    "role_name": "GDT",
    "address": "258 Nguyễn Chí Thanh st., Ba Vi dist, Thanh Hoa, Vietnam",
    "phone": "0201174190",
    "email": "nqhaiphong_manager@magicpost.transaction.com",
    "deleted": false,
    "__v": 0
  },
  {
    "user_name": "DGD_NQ_HaiPhong_Employee1",
    "name": "Nguyễn Duy Ngọc",
    "password": "111",
    "center_name": "DGD_NQ_HaiPhong",
    "role_name": "GDV",
    "address": "232 Nguyễn Chí Thanh st., Long Bien dist, Kon Tum, Vietnam",
    "phone": "0503156416",
    "email": "nqhaiphong_employee1@magicpost.transaction.com",
    "deleted": false,
    "__v": 0
  },
  {
    "user_name": "DGD_NQ_HaiPhong_Employee2",
    "name": "Trần Thu Anh",
    "password": "111",
    "center_name": "DGD_NQ_HaiPhong",
    "role_name": "GDV",
    "address": "142 Vạn Phúc st., Cau Giay dist, Hai Phong, Vietnam",
    "phone": "0187021504",
    "email": "nqhaiphong_employee2@magicpost.transaction.com",
    "deleted": false,
    "__v": 0
  },
  {
    "user_name": "DGD_LC_HaiPhong_Manager",
    "name": "Trần Duy Huyền",
    "password": "111",
    "center_name": "DGD_LC_HaiPhong",
    "role_name": "GDT",
    "address": "282 Trần Hưng Đạo st., Thach That dist, Ho Chi Minh, Vietnam",
    "phone": "0800723093",
    "email": "lchaiphong_manager@magicpost.transaction.com",
    "deleted": false,
    "__v": 0
  },
  {
    "user_name": "DGD_LC_HaiPhong_Employee1",
    "name": "Nguyễn Duy Hùng",
    "password": "111",
    "center_name": "DGD_LC_HaiPhong",
    "role_name": "GDV",
    "address": "151 Trần Hưng Đạo st., Long Bien dist, Thanh Hoa, Vietnam",
    "phone": "0822448704",
    "email": "lchaiphong_employee1@magicpost.transaction.com",
    "deleted": false,
    "__v": 0
  },
  {
    "user_name": "DGD_LC_HaiPhong_Employee2",
    "name": "Hoàng Minh Anh",
    "password": "111",
    "center_name": "DGD_LC_HaiPhong",
    "role_name": "GDV",
    "address": "280 Ngọc Hà st., Long Bien dist, Ho Chi Minh, Vietnam",
    "phone": "0404904640",
    "email": "lchaiphong_employee2@magicpost.transaction.com",
    "deleted": false,
    "__v": 0
  },
  {
    "user_name": "DGD_ML_NamDinh_Manager",
    "name": "Trần Duy Huyền",
    "password": "111",
    "center_name": "DGD_ML_NamDinh",
    "role_name": "GDT",
    "address": "214 Mai Anh Tuấn st., Ba Vi dist, Khanh Hoa, Vietnam",
    "phone": "0572296684",
    "email": "mlnamdinh_manager@magicpost.transaction.com",
    "deleted": false,
    "__v": 0
  },
  {
    "user_name": "DGD_ML_NamDinh_Employee1",
    "name": "Hoàng Minh Hùng",
    "password": "111",
    "center_name": "DGD_ML_NamDinh",
    "role_name": "GDV",
    "address": "50 Trần Hưng Đạo st., Long Bien dist, Hai Phong, Vietnam",
    "phone": "0078229094",
    "email": "mlnamdinh_employee1@magicpost.transaction.com",
    "deleted": false,
    "__v": 0
  },
  {
    "user_name": "DGD_ML_NamDinh_Employee2",
    "name": "Hoàng Duy Duy",
    "password": "111",
    "center_name": "DGD_ML_NamDinh",
    "role_name": "GDV",
    "address": "134 Nguyễn Trung Trực st., Cau Giay dist, Nam Dinh, Vietnam",
    "phone": "0887249749",
    "email": "mlnamdinh_employee2@magicpost.transaction.com",
    "deleted": false,
    "__v": 0
  },
  {
    "user_name": "DGD_NH_NamDinh_Manager",
    "name": "Phạm Minh Ngọc",
    "password": "111",
    "center_name": "DGD_NH_NamDinh",
    "role_name": "GDT",
    "address": "211 Nguyễn Thái Học st., Hoang Mai dist, Da Nang, Vietnam",
    "phone": "0822099986",
    "email": "nhnamdinh_manager@magicpost.transaction.com",
    "deleted": false,
    "__v": 0
  },
  {
    "user_name": "DGD_NH_NamDinh_Employee1",
    "name": "Đinh Thu Ngọc",
    "password": "111",
    "center_name": "DGD_NH_NamDinh",
    "role_name": "GDV",
    "address": "46 Vạn Phúc st., Son Tay dist, Thanh Hoa, Vietnam",
    "phone": "0052184464",
    "email": "nhnamdinh_employee1@magicpost.transaction.com",
    "deleted": false,
    "__v": 0
  },
  {
    "user_name": "DGD_NH_NamDinh_Employee2",
    "name": "Phạm Văn Hùng",
    "password": "111",
    "center_name": "DGD_NH_NamDinh",
    "role_name": "GDV",
    "address": "202 Nguyễn Thái Học st., Phu Xuyen dist, Thanh Hoa, Vietnam",
    "phone": "0212313840",
    "email": "nhnamdinh_employee2@magicpost.transaction.com",
    "deleted": false,
    "__v": 0
  },
  {
    "user_name": "DGD_XT_NamDinh_Manager",
    "name": "Nguyễn Duy Huyền",
    "password": "111",
    "center_name": "DGD_XT_NamDinh",
    "role_name": "GDT",
    "address": "242 Mai Anh Tuấn st., Thach That dist, Kon Tum, Vietnam",
    "phone": "0650980382",
    "email": "xtnamdinh_manager@magicpost.transaction.com",
    "deleted": false,
    "__v": 0
  },
  {
    "user_name": "DGD_XT_NamDinh_Employee1",
    "name": "Đinh Duy Hùng",
    "password": "111",
    "center_name": "DGD_XT_NamDinh",
    "role_name": "GDV",
    "address": "175 Nguyễn Chí Thanh st., Soc Son dist, Da Nang, Vietnam",
    "phone": "0867075561",
    "email": "xtnamdinh_employee1@magicpost.transaction.com",
    "deleted": false,
    "__v": 0
  },
  {
    "user_name": "DGD_XT_NamDinh_Employee2",
    "name": "Phạm Duy Anh",
    "password": "111",
    "center_name": "DGD_XT_NamDinh",
    "role_name": "GDV",
    "address": "284 Phan Đình Phùng st., Soc Son dist, Da Nang, Vietnam",
    "phone": "0351114317",
    "email": "xtnamdinh_employee2@magicpost.transaction.com",
    "deleted": false,
    "__v": 0
  },
  {
    "user_name": "DGD_SS_ThanhHoa_Manager",
    "name": "Nguyễn Thu Ngọc",
    "password": "111",
    "center_name": "DGD_SS_ThanhHoa",
    "role_name": "GDT",
    "address": "50 Nguyễn Chí Thanh st., Thanh Tri dist, Hai Phong, Vietnam",
    "phone": "0385969381",
    "email": "ssthanhhoa_manager@magicpost.transaction.com",
    "deleted": false,
    "__v": 0
  },
  {
    "user_name": "DGD_SS_ThanhHoa_Employee1",
    "name": "Phạm Thu Hùng",
    "password": "111",
    "center_name": "DGD_SS_ThanhHoa",
    "role_name": "GDV",
    "address": "221 Vạn Bảo st., Thanh Tri dist, Ho Chi Minh, Vietnam",
    "phone": "0466513509",
    "email": "ssthanhhoa_employee1@magicpost.transaction.com",
    "deleted": false,
    "__v": 0
  },
  {
    "user_name": "DGD_SS_ThanhHoa_Employee2",
    "name": "Nguyễn Thu Hùng",
    "password": "111",
    "center_name": "DGD_SS_ThanhHoa",
    "role_name": "GDV",
    "address": "96 Kim Mã st., Cau Giay dist, Ha Noi, Vietnam",
    "phone": "0476611372",
    "email": "ssthanhhoa_employee2@magicpost.transaction.com",
    "deleted": false,
    "__v": 0
  },
  {
    "user_name": "DGD_HT_ThanhHoa_Manager",
    "name": "Trần Thu Ngọc",
    "password": "111",
    "center_name": "DGD_HT_ThanhHoa",
    "role_name": "GDT",
    "address": "54 Thái Hà st., Thach That dist, Hai Phong, Vietnam",
    "phone": "0474469224",
    "email": "htthanhhoa_manager@magicpost.transaction.com",
    "deleted": false,
    "__v": 0
  },
  {
    "user_name": "DGD_HT_ThanhHoa_Employee1",
    "name": "Hoàng Duy Hùng",
    "password": "111",
    "center_name": "DGD_HT_ThanhHoa",
    "role_name": "GDV",
    "address": "65 Kim Mã st., Thach That dist, Da Nang, Vietnam",
    "phone": "0575627747",
    "email": "htthanhhoa_employee1@magicpost.transaction.com",
    "deleted": false,
    "__v": 0
  },
  {
    "user_name": "DGD_HT_ThanhHoa_Employee2",
    "name": "Phạm Văn Anh",
    "password": "111",
    "center_name": "DGD_HT_ThanhHoa",
    "role_name": "GDV",
    "address": "186 Vạn Phúc st., Son Tay dist, Da Nang, Vietnam",
    "phone": "0101608951",
    "email": "htthanhhoa_employee2@magicpost.transaction.com",
    "deleted": false,
    "__v": 0
  },
  {
    "user_name": "DGD_VL_ThanhHoa_Manager",
    "name": "Phạm Minh Duy",
    "password": "111",
    "center_name": "DGD_VL_ThanhHoa",
    "role_name": "GDT",
    "address": "298 Ngọc Hà st., Tay Ho dist, Ho Chi Minh, Vietnam",
    "phone": "0014768938",
    "email": "vlthanhhoa_manager@magicpost.transaction.com",
    "deleted": false,
    "__v": 0
  },
  {
    "user_name": "DGD_VL_ThanhHoa_Employee1",
    "name": "Nguyễn Văn Ngọc",
    "password": "111",
    "center_name": "DGD_VL_ThanhHoa",
    "role_name": "GDV",
    "address": "91 Nguyễn Văn Ngọc st., Me Linh dist, Nam Dinh, Vietnam",
    "phone": "0169243517",
    "email": "vlthanhhoa_employee1@magicpost.transaction.com",
    "deleted": false,
    "__v": 0
  },
  {
    "user_name": "DGD_VL_ThanhHoa_Employee2",
    "name": "Phạm Minh Ngọc",
    "password": "111",
    "center_name": "DGD_VL_ThanhHoa",
    "role_name": "GDV",
    "address": "220 Trần Hưng Đạo st., Me Linh dist, Ha Noi, Vietnam",
    "phone": "0683269103",
    "email": "vlthanhhoa_employee2@magicpost.transaction.com",
    "deleted": false,
    "__v": 0
  },
  {
    "user_name": "DGD_ST_DaNang_Manager",
    "name": "Nguyễn Duy Huyền",
    "password": "111",
    "center_name": "DGD_ST_DaNang",
    "role_name": "GDT",
    "address": "89 Yên Thế st., Soc Son dist, Ha Noi, Vietnam",
    "phone": "0328865462",
    "email": "stdanang_manager@magicpost.transaction.com",
    "deleted": false,
    "__v": 0
  },
  {
    "user_name": "DGD_ST_DaNang_Employee1",
    "name": "Trần Thu Ngọc",
    "password": "111",
    "center_name": "DGD_ST_DaNang",
    "role_name": "GDV",
    "address": "188 Ngọc Hà st., Son Tay dist, Ha Noi, Vietnam",
    "phone": "0008149276",
    "email": "stdanang_employee1@magicpost.transaction.com",
    "deleted": false,
    "__v": 0
  },
  {
    "user_name": "DGD_ST_DaNang_Employee2",
    "name": "Nguyễn Minh Ngọc",
    "password": "111",
    "center_name": "DGD_ST_DaNang",
    "role_name": "GDV",
    "address": "217 Nguyễn Trung Trực st., Tay Ho dist, Khanh Hoa, Vietnam",
    "phone": "0093875894",
    "email": "stdanang_employee2@magicpost.transaction.com",
    "deleted": false,
    "__v": 0
  },
  {
    "user_name": "DGD_CL_DaNang_Manager",
    "name": "Hoàng Văn Hùng",
    "password": "111",
    "center_name": "DGD_CL_DaNang",
    "role_name": "GDT",
    "address": "247 Trần Duy Hưng st., Quoc Oai dist, Thanh Hoa, Vietnam",
    "phone": "0215536367",
    "email": "cldanang_manager@magicpost.transaction.com",
    "deleted": false,
    "__v": 0
  },
  {
    "user_name": "DGD_CL_DaNang_Employee1",
    "name": "Phạm Văn Ngọc",
    "password": "111",
    "center_name": "DGD_CL_DaNang",
    "role_name": "GDV",
    "address": "19 Nguyễn Thái Học st., Tay Ho dist, Khanh Hoa, Vietnam",
    "phone": "0481205721",
    "email": "cldanang_employee1@magicpost.transaction.com",
    "deleted": false,
    "__v": 0
  },
  {
    "user_name": "DGD_CL_DaNang_Employee2",
    "name": "Đinh Minh Ngọc",
    "password": "111",
    "center_name": "DGD_CL_DaNang",
    "role_name": "GDV",
    "address": "211 Nguyễn Chí Thanh st., Phu Xuyen dist, Ho Chi Minh, Vietnam",
    "phone": "0587427805",
    "email": "cldanang_employee2@magicpost.transaction.com",
    "deleted": false,
    "__v": 0
  },
  {
    "user_name": "DGD_HC_DaNang_Manager",
    "name": "Nguyễn Minh Duy",
    "password": "111",
    "center_name": "DGD_HC_DaNang",
    "role_name": "GDT",
    "address": "42 Thái Hà st., Hoang Mai dist, Kon Tum, Vietnam",
    "phone": "0386927582",
    "email": "hcdanang_manager@magicpost.transaction.com",
    "deleted": false,
    "__v": 0
  },
  {
    "user_name": "DGD_HC_DaNang_Employee1",
    "name": "Phạm Duy Anh",
    "password": "111",
    "center_name": "DGD_HC_DaNang",
    "role_name": "GDV",
    "address": "121 Trúc Bạch st., Thanh Xuan dist, Da Nang, Vietnam",
    "phone": "0440827951",
    "email": "hcdanang_employee1@magicpost.transaction.com",
    "deleted": false,
    "__v": 0
  },
  {
    "user_name": "DGD_HC_DaNang_Employee2",
    "name": "Trần Minh Anh",
    "password": "111",
    "center_name": "DGD_HC_DaNang",
    "role_name": "GDV",
    "address": "143 Cửa Bắc st., Thanh Xuan dist, Da Nang, Vietnam",
    "phone": "0647940339",
    "email": "hcdanang_employee2@magicpost.transaction.com",
    "deleted": false,
    "__v": 0
  },
  {
    "user_name": "DGD_DH_KonTum_Manager",
    "name": "Đinh Duy Hùng",
    "password": "111",
    "center_name": "DGD_DH_KonTum",
    "role_name": "GDT",
    "address": "276 Trúc Bạch st., Tay Ho dist, Da Nang, Vietnam",
    "phone": "0448494024",
    "email": "dhkontum_manager@magicpost.transaction.com",
    "deleted": false,
    "__v": 0
  },
  {
    "user_name": "DGD_DH_KonTum_Employee1",
    "name": "Phạm Duy Hùng",
    "password": "111",
    "center_name": "DGD_DH_KonTum",
    "role_name": "GDV",
    "address": "184 Vạn Bảo st., Thanh Xuan dist, Khanh Hoa, Vietnam",
    "phone": "0836574264",
    "email": "dhkontum_employee1@magicpost.transaction.com",
    "deleted": false,
    "__v": 0
  },
  {
    "user_name": "DGD_DH_KonTum_Employee2",
    "name": "Trần Duy Anh",
    "password": "111",
    "center_name": "DGD_DH_KonTum",
    "role_name": "GDV",
    "address": "139 Phan Đình Phùng st., Quoc Oai dist, Nam Dinh, Vietnam",
    "phone": "0809913103",
    "email": "dhkontum_employee2@magicpost.transaction.com",
    "deleted": false,
    "__v": 0
  },
  {
    "user_name": "DGD_NH_KonTum_Manager",
    "name": "Trần Duy Huyền",
    "password": "111",
    "center_name": "DGD_NH_KonTum",
    "role_name": "GDT",
    "address": "42 Nguyễn Chí Thanh st., Thanh Xuan dist, Khanh Hoa, Vietnam",
    "phone": "0918299266",
    "email": "nhkontum_manager@magicpost.transaction.com",
    "deleted": false,
    "__v": 0
  },
  {
    "user_name": "DGD_NH_KonTum_Employee1",
    "name": "Trần Minh Duy",
    "password": "111",
    "center_name": "DGD_NH_KonTum",
    "role_name": "GDV",
    "address": "13 Núi Trúc st., Phu Xuyen dist, Ho Chi Minh, Vietnam",
    "phone": "0320699088",
    "email": "nhkontum_employee1@magicpost.transaction.com",
    "deleted": false,
    "__v": 0
  },
  {
    "user_name": "DGD_NH_KonTum_Employee2",
    "name": "Phạm Thu Duy",
    "password": "111",
    "center_name": "DGD_NH_KonTum",
    "role_name": "GDV",
    "address": "147 Sơn Tây st., Tay Ho dist, Nam Dinh, Vietnam",
    "phone": "0020544350",
    "email": "nhkontum_employee2@magicpost.transaction.com",
    "deleted": false,
    "__v": 0
  },
  {
    "user_name": "DGD_DG_KonTum_Manager",
    "name": "Trần Thu Anh",
    "password": "111",
    "center_name": "DGD_DG_KonTum",
    "role_name": "GDT",
    "address": "157 Thái Hà st., Quoc Oai dist, Kon Tum, Vietnam",
    "phone": "0973608540",
    "email": "dgkontum_manager@magicpost.transaction.com",
    "deleted": false,
    "__v": 0
  },
  {
    "user_name": "DGD_DG_KonTum_Employee1",
    "name": "Trần Minh Anh",
    "password": "111",
    "center_name": "DGD_DG_KonTum",
    "role_name": "GDV",
    "address": "71 Vạn Phúc st., Cau Giay dist, Kon Tum, Vietnam",
    "phone": "0280909120",
    "email": "dgkontum_employee1@magicpost.transaction.com",
    "deleted": false,
    "__v": 0
  },
  {
    "user_name": "DGD_DG_KonTum_Employee2",
    "name": "Trần Thu Duy",
    "password": "111",
    "center_name": "DGD_DG_KonTum",
    "role_name": "GDV",
    "address": "50 Nguyễn Chí Thanh st., Tay Ho dist, Kon Tum, Vietnam",
    "phone": "0979379854",
    "email": "dgkontum_employee2@magicpost.transaction.com",
    "deleted": false,
    "__v": 0
  },
  {
    "user_name": "DGD_NT_KhanhHoa_Manager",
    "name": "Nguyễn Duy Anh",
    "password": "111",
    "center_name": "DGD_NT_KhanhHoa",
    "role_name": "GDT",
    "address": "71 Hoàng Hoa Thám st., Soc Son dist, Hai Phong, Vietnam",
    "phone": "0011970344",
    "email": "ntkhanhhoa_manager@magicpost.transaction.com",
    "deleted": false,
    "__v": 0
  },
  {
    "user_name": "DGD_NT_KhanhHoa_Employee1",
    "name": "Đinh Duy Anh",
    "password": "111",
    "center_name": "DGD_NT_KhanhHoa",
    "role_name": "GDV",
    "address": "142 Cửa Bắc st., Son Tay dist, Da Nang, Vietnam",
    "phone": "0640258740",
    "email": "ntkhanhhoa_employee1@magicpost.transaction.com",
    "deleted": false,
    "__v": 0
  },
  {
    "user_name": "DGD_NT_KhanhHoa_Employee2",
    "name": "Trần Minh Huyền",
    "password": "111",
    "center_name": "DGD_NT_KhanhHoa",
    "role_name": "GDV",
    "address": "117 Trần Hưng Đạo st., Tay Ho dist, Kon Tum, Vietnam",
    "phone": "0128589247",
    "email": "ntkhanhhoa_employee2@magicpost.transaction.com",
    "deleted": false,
    "__v": 0
  },
  {
    "user_name": "DGD_VN_KhanhHoa_Manager",
    "name": "Trần Minh Hùng",
    "password": "111",
    "center_name": "DGD_VN_KhanhHoa",
    "role_name": "GDT",
    "address": "172 Núi Trúc st., Me Linh dist, Thanh Hoa, Vietnam",
    "phone": "0088325355",
    "email": "vnkhanhhoa_manager@magicpost.transaction.com",
    "deleted": false,
    "__v": 0
  },
  {
    "user_name": "DGD_VN_KhanhHoa_Employee1",
    "name": "Nguyễn Thu Anh",
    "password": "111",
    "center_name": "DGD_VN_KhanhHoa",
    "role_name": "GDV",
    "address": "155 Cửa Bắc st., Thach That dist, Nam Dinh, Vietnam",
    "phone": "0220664570",
    "email": "vnkhanhhoa_employee1@magicpost.transaction.com",
    "deleted": false,
    "__v": 0
  },
  {
    "user_name": "DGD_VN_KhanhHoa_Employee2",
    "name": "Phạm Văn Huyền",
    "password": "111",
    "center_name": "DGD_VN_KhanhHoa",
    "role_name": "GDV",
    "address": "282 Nguyễn Trung Trực st., Phu Xuyen dist, Khanh Hoa, Vietnam",
    "phone": "0058154130",
    "email": "vnkhanhhoa_employee2@magicpost.transaction.com",
    "deleted": false,
    "__v": 0
  },
  {
    "user_name": "DGD_CR_KhanhHoa_Manager",
    "name": "Nguyễn Thu Ngọc",
    "password": "111",
    "center_name": "DGD_CR_KhanhHoa",
    "role_name": "GDT",
    "address": "111 Thái Hà st., Cau Giay dist, Ho Chi Minh, Vietnam",
    "phone": "0759012183",
    "email": "crkhanhhoa_manager@magicpost.transaction.com",
    "deleted": false,
    "__v": 0
  },
  {
    "user_name": "DGD_CR_KhanhHoa_Employee1",
    "name": "Đinh Duy Huyền",
    "password": "111",
    "center_name": "DGD_CR_KhanhHoa",
    "role_name": "GDV",
    "address": "34 Kim Mã st., Long Bien dist, Hai Phong, Vietnam",
    "phone": "0963842012",
    "email": "crkhanhhoa_employee1@magicpost.transaction.com",
    "deleted": false,
    "__v": 0
  },
  {
    "user_name": "DGD_CR_KhanhHoa_Employee2",
    "name": "Nguyễn Duy Hùng",
    "password": "111",
    "center_name": "DGD_CR_KhanhHoa",
    "role_name": "GDV",
    "address": "238 Vạn Bảo st., Son Tay dist, Ha Noi, Vietnam",
    "phone": "0541586339",
    "email": "crkhanhhoa_employee2@magicpost.transaction.com",
    "deleted": false,
    "__v": 0
  },
  {
    "user_name": "DGD_BT_HoChiMinh_Manager",
    "name": "Đinh Văn Anh",
    "password": "111",
    "center_name": "DGD_BT_HoChiMinh",
    "role_name": "GDT",
    "address": "169 Vạn Bảo st., Thanh Xuan dist, Ho Chi Minh, Vietnam",
    "phone": "0643764574",
    "email": "bthochiminh_manager@magicpost.transaction.com",
    "deleted": false,
    "__v": 0
  },
  {
    "user_name": "DGD_BT_HoChiMinh_Employee1",
    "name": "Nguyễn Minh Ngọc",
    "password": "111",
    "center_name": "DGD_BT_HoChiMinh",
    "role_name": "GDV",
    "address": "70 Nguyễn Thái Học st., Son Tay dist, Ha Noi, Vietnam",
    "phone": "0067540993",
    "email": "bthochiminh_employee1@magicpost.transaction.com",
    "deleted": false,
    "__v": 0
  },
  {
    "user_name": "DGD_BT_HoChiMinh_Employee2",
    "name": "Trần Duy Huyền",
    "password": "111",
    "center_name": "DGD_BT_HoChiMinh",
    "role_name": "GDV",
    "address": "76 Vạn Bảo st., Son Tay dist, Kon Tum, Vietnam",
    "phone": "0217632998",
    "email": "bthochiminh_employee2@magicpost.transaction.com",
    "deleted": false,
    "__v": 0
  },
  {
    "user_name": "DGD_TD_HoChiMinh_Manager",
    "name": "Đinh Thu Anh",
    "password": "111",
    "center_name": "DGD_TD_HoChiMinh",
    "role_name": "GDT",
    "address": "19 Núi Trúc st., Ba Vi dist, Nam Dinh, Vietnam",
    "phone": "0654094066",
    "email": "tdhochiminh_manager@magicpost.transaction.com",
    "deleted": false,
    "__v": 0
  },
  {
    "user_name": "DGD_TD_HoChiMinh_Employee1",
    "name": "Nguyễn Thu Huyền",
    "password": "111",
    "center_name": "DGD_TD_HoChiMinh",
    "role_name": "GDV",
    "address": "12 Nguyễn Văn Ngọc st., Thanh Tri dist, Ha Noi, Vietnam",
    "phone": "0283864896",
    "email": "tdhochiminh_employee1@magicpost.transaction.com",
    "deleted": false,
    "__v": 0
  },
  {
    "user_name": "DGD_TD_HoChiMinh_Employee2",
    "name": "Trần Thu Hùng",
    "password": "111",
    "center_name": "DGD_TD_HoChiMinh",
    "role_name": "GDV",
    "address": "119 Mai Anh Tuấn st., Thach That dist, Hai Phong, Vietnam",
    "phone": "0559253128",
    "email": "tdhochiminh_employee2@magicpost.transaction.com",
    "deleted": false,
    "__v": 0
  },
  {
    "user_name": "DGD_Q1_HoChiMinh_Manager",
    "name": "Phạm Minh Hùng",
    "password": "111",
    "center_name": "DGD_Q1_HoChiMinh",
    "role_name": "GDT",
    "address": "266 Ngọc Hà st., Thach That dist, Ho Chi Minh, Vietnam",
    "phone": "0484568819",
    "email": "q1hochiminh_manager@magicpost.transaction.com",
    "deleted": false,
    "__v": 0
  },
  {
    "user_name": "DGD_Q1_HoChiMinh_Employee1",
    "name": "Hoàng Minh Ngọc",
    "password": "111",
    "center_name": "DGD_Q1_HoChiMinh",
    "role_name": "GDV",
    "address": "238 Núi Trúc st., Thach That dist, Da Nang, Vietnam",
    "phone": "0865263361",
    "email": "q1hochiminh_employee1@magicpost.transaction.com",
    "deleted": false,
    "__v": 0
  },
  {
    "user_name": "DGD_Q1_HoChiMinh_Employee2",
    "name": "Hoàng Duy Ngọc",
    "password": "111",
    "center_name": "DGD_Q1_HoChiMinh",
    "role_name": "GDV",
    "address": "129 Cửa Bắc st., Quoc Oai dist, Da Nang, Vietnam",
    "phone": "0460572097",
    "email": "q1hochiminh_employee2@magicpost.transaction.com",
    "deleted": false,
    "__v": 0
  },
  {
    "user_name": "DTK_Hanoi_Manager",
    "name": "Hoàng Minh Ngọc",
    "password": "111",
    "center_name": "DTK_Hanoi",
    "role_name": "TKT",
    "address": "219 Phan Đình Phùng st., Me Linh dist, Da Nang, Vietnam",
    "phone": "0940276040",
    "email": "hanoi_manager@magicpost.collection.com",
    "deleted": false,
    "__v": 0
  },
  {
    "user_name": "DTK_Hanoi_Employee1",
    "name": "Đinh Duy Ngọc",
    "password": "111",
    "center_name": "DTK_Hanoi",
    "role_name": "TKV",
    "address": "145 Nguyễn Thái Học st., Me Linh dist, Da Nang, Vietnam",
    "phone": "0370747247",
    "email": "hanoi_employee1@magicpost.collection.com",
    "deleted": false,
    "__v": 0
  },
  {
    "user_name": "DTK_Hanoi_Employee2",
    "name": "Đinh Duy Huyền",
    "password": "111",
    "center_name": "DTK_Hanoi",
    "role_name": "TKV",
    "address": "171 Nguyễn Trung Trực st., Thanh Xuan dist, Khanh Hoa, Vietnam",
    "phone": "0629585150",
    "email": "hanoi_employee2@magicpost.collection.com",
    "deleted": false,
    "__v": 0
  },
  {
    "user_name": "DTK_HaiPhong_Manager",
    "name": "Phạm Văn Hùng",
    "password": "111",
    "center_name": "DTK_HaiPhong",
    "role_name": "TKT",
    "address": "72 Phan Đình Phùng st., Tay Ho dist, Thanh Hoa, Vietnam",
    "phone": "0678769351",
    "email": "haiphong_manager@magicpost.collection.com",
    "deleted": false,
    "__v": 0
  },
  {
    "user_name": "DTK_HaiPhong_Employee1",
    "name": "Đinh Minh Duy",
    "password": "111",
    "center_name": "DTK_HaiPhong",
    "role_name": "TKV",
    "address": "171 Mai Anh Tuấn st., Long Bien dist, Thanh Hoa, Vietnam",
    "phone": "0145935118",
    "email": "haiphong_employee1@magicpost.collection.com",
    "deleted": false,
    "__v": 0
  },
  {
    "user_name": "DTK_HaiPhong_Employee2",
    "name": "Trần Văn Duy",
    "password": "111",
    "center_name": "DTK_HaiPhong",
    "role_name": "TKV",
    "address": "40 Nguyễn Chí Thanh st., Thanh Tri dist, Thanh Hoa, Vietnam",
    "phone": "0680914410",
    "email": "haiphong_employee2@magicpost.collection.com",
    "deleted": false,
    "__v": 0
  },
  {
    "user_name": "DTK_NamDinh_Manager",
    "name": "Nguyễn Văn Hùng",
    "password": "111",
    "center_name": "DTK_NamDinh",
    "role_name": "TKT",
    "address": "271 Nguyễn Chí Thanh st., Hoang Mai dist, Hai Phong, Vietnam",
    "phone": "0676186854",
    "email": "namdinh_manager@magicpost.collection.com",
    "deleted": false,
    "__v": 0
  },
  {
    "user_name": "DTK_NamDinh_Employee1",
    "name": "Nguyễn Duy Hùng",
    "password": "111",
    "center_name": "DTK_NamDinh",
    "role_name": "TKV",
    "address": "288 Cửa Bắc st., Quoc Oai dist, Nam Dinh, Vietnam",
    "phone": "0782265270",
    "email": "namdinh_employee1@magicpost.collection.com",
    "deleted": false,
    "__v": 0
  },
  {
    "user_name": "DTK_NamDinh_Employee2",
    "name": "Trần Thu Duy",
    "password": "111",
    "center_name": "DTK_NamDinh",
    "role_name": "TKV",
    "address": "16 Nguyễn Trung Trực st., Me Linh dist, Da Nang, Vietnam",
    "phone": "0033341592",
    "email": "namdinh_employee2@magicpost.collection.com",
    "deleted": false,
    "__v": 0
  },
  {
    "user_name": "DTK_ThanhHoa_Manager",
    "name": "Phạm Duy Hùng",
    "password": "111",
    "center_name": "DTK_ThanhHoa",
    "role_name": "TKT",
    "address": "193 Vạn Bảo st., Tay Ho dist, Ha Noi, Vietnam",
    "phone": "0776601846",
    "email": "thanhhoa_manager@magicpost.collection.com",
    "deleted": false,
    "__v": 0
  },
  {
    "user_name": "DTK_ThanhHoa_Employee1",
    "name": "Đinh Văn Huyền",
    "password": "111",
    "center_name": "DTK_ThanhHoa",
    "role_name": "TKV",
    "address": "107 Phan Đình Phùng st., Quoc Oai dist, Ha Noi, Vietnam",
    "phone": "0003586388",
    "email": "thanhhoa_employee1@magicpost.collection.com",
    "deleted": false,
    "__v": 0
  },
  {
    "user_name": "DTK_ThanhHoa_Employee2",
    "name": "Trần Duy Anh",
    "password": "111",
    "center_name": "DTK_ThanhHoa",
    "role_name": "TKV",
    "address": "194 Vạn Bảo st., Thach That dist, Ho Chi Minh, Vietnam",
    "phone": "0538012222",
    "email": "thanhhoa_employee2@magicpost.collection.com",
    "deleted": false,
    "__v": 0
  },
  {
    "user_name": "DTK_DaNang_Manager",
    "name": "Trần Duy Anh",
    "password": "111",
    "center_name": "DTK_DaNang",
    "role_name": "TKT",
    "address": "265 Phan Đình Phùng st., Thanh Xuan dist, Da Nang, Vietnam",
    "phone": "0113815169",
    "email": "danang_manager@magicpost.collection.com",
    "deleted": false,
    "__v": 0
  },
  {
    "user_name": "DTK_DaNang_Employee1",
    "name": "Phạm Minh Anh",
    "password": "111",
    "center_name": "DTK_DaNang",
    "role_name": "TKV",
    "address": "67 Vạn Phúc st., Tay Ho dist, Khanh Hoa, Vietnam",
    "phone": "0729081410",
    "email": "danang_employee1@magicpost.collection.com",
    "deleted": false,
    "__v": 0
  },
  {
    "user_name": "DTK_DaNang_Employee2",
    "name": "Nguyễn Văn Huyền",
    "password": "111",
    "center_name": "DTK_DaNang",
    "role_name": "TKV",
    "address": "154 Sơn Tây st., Me Linh dist, Ha Noi, Vietnam",
    "phone": "0438249046",
    "email": "danang_employee2@magicpost.collection.com",
    "deleted": false,
    "__v": 0
  },
  {
    "user_name": "DTK_KonTum_Manager",
    "name": "Nguyễn Minh Huyền",
    "password": "111",
    "center_name": "DTK_KonTum",
    "role_name": "TKT",
    "address": "197 Nguyễn Thái Học st., Thanh Tri dist, Thanh Hoa, Vietnam",
    "phone": "0896132731",
    "email": "kontum_manager@magicpost.collection.com",
    "deleted": false,
    "__v": 0
  },
  {
    "user_name": "DTK_KonTum_Employee1",
    "name": "Phạm Minh Anh",
    "password": "111",
    "center_name": "DTK_KonTum",
    "role_name": "TKV",
    "address": "99 Sơn Tây st., Thach That dist, Ho Chi Minh, Vietnam",
    "phone": "0961524236",
    "email": "kontum_employee1@magicpost.collection.com",
    "deleted": false,
    "__v": 0
  },
  {
    "user_name": "DTK_KonTum_Employee2",
    "name": "Hoàng Văn Huyền",
    "password": "111",
    "center_name": "DTK_KonTum",
    "role_name": "TKV",
    "address": "94 Thái Hà st., Quoc Oai dist, Nam Dinh, Vietnam",
    "phone": "0911337223",
    "email": "kontum_employee2@magicpost.collection.com",
    "deleted": false,
    "__v": 0
  },
  {
    "user_name": "DTK_KhanhHoa_Manager",
    "name": "Đinh Thu Huyền",
    "password": "111",
    "center_name": "DTK_KhanhHoa",
    "role_name": "TKT",
    "address": "33 Nguyễn Chí Thanh st., Soc Son dist, Khanh Hoa, Vietnam",
    "phone": "0171896210",
    "email": "khanhhoa_manager@magicpost.collection.com",
    "deleted": false,
    "__v": 0
  },
  {
    "user_name": "DTK_KhanhHoa_Employee1",
    "name": "Đinh Duy Anh",
    "password": "111",
    "center_name": "DTK_KhanhHoa",
    "role_name": "TKV",
    "address": "179 Trần Duy Hưng st., Thanh Tri dist, Kon Tum, Vietnam",
    "phone": "0090748931",
    "email": "khanhhoa_employee1@magicpost.collection.com",
    "deleted": false,
    "__v": 0
  },
  {
    "user_name": "DTK_KhanhHoa_Employee2",
    "name": "Đinh Duy Huyền",
    "password": "111",
    "center_name": "DTK_KhanhHoa",
    "role_name": "TKV",
    "address": "153 Đào Tấn st., Soc Son dist, Ho Chi Minh, Vietnam",
    "phone": "0651903418",
    "email": "khanhhoa_employee2@magicpost.collection.com",
    "deleted": false,
    "__v": 0
  },
  {
    "user_name": "DTK_HoChiMinh_Manager",
    "name": "Trần Minh Huyền",
    "password": "111",
    "center_name": "DTK_HoChiMinh",
    "role_name": "TKT",
    "address": "39 Trần Duy Hưng st., Hoang Mai dist, Kon Tum, Vietnam",
    "phone": "0636921168",
    "email": "hochiminh_manager@magicpost.collection.com",
    "deleted": false,
    "__v": 0
  },
  {
    "user_name": "DTK_HoChiMinh_Employee1",
    "name": "Đinh Văn Duy",
    "password": "111",
    "center_name": "DTK_HoChiMinh",
    "role_name": "TKV",
    "address": "94 Phan Đình Phùng st., Thanh Xuan dist, Ho Chi Minh, Vietnam",
    "phone": "0634137398",
    "email": "hochiminh_employee1@magicpost.collection.com",
    "deleted": false,
    "__v": 0
  },
  {
    "user_name": "DTK_HoChiMinh_Employee2",
    "name": "Trần Thu Ngọc",
    "password": "111",
    "center_name": "DTK_HoChiMinh",
    "role_name": "TKV",
    "address": "218 Yên Thế st., Phu Xuyen dist, Khanh Hoa, Vietnam",
    "phone": "0801051650",
    "email": "hochiminh_employee2@magicpost.collection.com",
    "deleted": false,
    "__v": 0
  }
]